devtool/__init__.py
devtool/devTool.py
devtool/main.py
devtool/style.yaml
devtool/tests/__init__.py
devtool/tests/testSystrace.py
devtool/tests/utils/__init__.py
devtool/tests/utils/func1.py
devtool/utils/__init__.py
devtool/utils/common.py
devtool/utils/devtool_exceptions.py
devtool/utils/getFunctions.py
devtool/utils/getModules.py
devtool/utils/pythonSearch.py
devtool/utils/pythonShow.py
DevTool-0.0.2.dist-info/LICENSE
DevTool-0.0.2.dist-info/METADATA
DevTool-0.0.2.dist-info/WHEEL
DevTool-0.0.2.dist-info/entry_points.txt
DevTool-0.0.2.dist-info/top_level.txt
DevTool-0.0.2.dist-info/zip-safe
DevTool-0.0.2.dist-info/RECORD
