Metadata-Version: 2.1
Name: DevTool
Version: 0.0.2
Summary: a small tool for python development
Home-page: https://github.com/guchengxi1994/dev-tool-for-python
Author: Chengxi GU
Author-email: guchengxi1994@qq.com
License: MIT License
Platform: UNKNOWN
Classifier: Programming Language :: Python
Classifier: Programming Language :: Python :: 3.7
Classifier: Programming Language :: Python :: 3.6
Requires-Dist: setuptools (==41.0.1)
Requires-Dist: termcolor (==1.1.0)
Requires-Dist: concurrent-log-handler (==0.9.16)
Requires-Dist: PyYAML (==5.1.1)
